{
  "openapi": "3.0.1",
  "info": {
    "title": "Avaliação Dev .net Sênior - Grupo Taking",
    "contact": {
      "name": "Glauber Q Maximiano",
      "email": "glauber.maximiano@gmail.com"
    },
    "version": "v1"
  },
  "paths": {
    "/api/AvaliacaoTaking/cliente": {
      "get": {
        "tags": [
          "Cliente"
        ],
        "parameters": [
          {
            "name": "idcSituacao",
            "in": "query",
            "schema": {
              "type": "string"
            }
          }
        ],
        "responses": {
          "200": {
            "description": "Success"
          }
        }
      },
      "post": {
        "tags": [
          "Cliente"
        ],
        "requestBody": {
          "content": {
            "application/json": {
              "schema": {
                "$ref": "#/components/schemas/ClienteDominio"
              }
            },
            "text/json": {
              "schema": {
                "$ref": "#/components/schemas/ClienteDominio"
              }
            },
            "application/*+json": {
              "schema": {
                "$ref": "#/components/schemas/ClienteDominio"
              }
            }
          }
        },
        "responses": {
          "200": {
            "description": "Success"
          }
        }
      },
      "put": {
        "tags": [
          "Cliente"
        ],
        "requestBody": {
          "content": {
            "application/json": {
              "schema": {
                "$ref": "#/components/schemas/ClienteDominio"
              }
            },
            "text/json": {
              "schema": {
                "$ref": "#/components/schemas/ClienteDominio"
              }
            },
            "application/*+json": {
              "schema": {
                "$ref": "#/components/schemas/ClienteDominio"
              }
            }
          }
        },
        "responses": {
          "200": {
            "description": "Success"
          }
        }
      }
    },
    "/api/AvaliacaoTaking/cliente/{Id}": {
      "get": {
        "tags": [
          "Cliente"
        ],
        "parameters": [
          {
            "name": "Id",
            "in": "path",
            "required": true,
            "schema": {
              "type": "integer",
              "format": "int32"
            }
          }
        ],
        "responses": {
          "200": {
            "description": "Success"
          }
        }
      },
      "delete": {
        "tags": [
          "Cliente"
        ],
        "parameters": [
          {
            "name": "Id",
            "in": "path",
            "required": true,
            "schema": {
              "type": "integer",
              "format": "int32"
            }
          }
        ],
        "responses": {
          "200": {
            "description": "Success"
          }
        }
      }
    },
    "/api/AvaliacaoTaking/filial": {
      "get": {
        "tags": [
          "Filial"
        ],
        "parameters": [
          {
            "name": "idcSituacao",
            "in": "query",
            "schema": {
              "type": "string"
            }
          }
        ],
        "responses": {
          "200": {
            "description": "Success"
          }
        }
      },
      "post": {
        "tags": [
          "Filial"
        ],
        "requestBody": {
          "content": {
            "application/json": {
              "schema": {
                "$ref": "#/components/schemas/FilialDominio"
              }
            },
            "text/json": {
              "schema": {
                "$ref": "#/components/schemas/FilialDominio"
              }
            },
            "application/*+json": {
              "schema": {
                "$ref": "#/components/schemas/FilialDominio"
              }
            }
          }
        },
        "responses": {
          "200": {
            "description": "Success"
          }
        }
      },
      "put": {
        "tags": [
          "Filial"
        ],
        "requestBody": {
          "content": {
            "application/json": {
              "schema": {
                "$ref": "#/components/schemas/FilialDominio"
              }
            },
            "text/json": {
              "schema": {
                "$ref": "#/components/schemas/FilialDominio"
              }
            },
            "application/*+json": {
              "schema": {
                "$ref": "#/components/schemas/FilialDominio"
              }
            }
          }
        },
        "responses": {
          "200": {
            "description": "Success"
          }
        }
      }
    },
    "/api/AvaliacaoTaking/filial/{Id}": {
      "get": {
        "tags": [
          "Filial"
        ],
        "parameters": [
          {
            "name": "Id",
            "in": "path",
            "required": true,
            "schema": {
              "type": "integer",
              "format": "int32"
            }
          }
        ],
        "responses": {
          "200": {
            "description": "Success"
          }
        }
      },
      "delete": {
        "tags": [
          "Filial"
        ],
        "parameters": [
          {
            "name": "Id",
            "in": "path",
            "required": true,
            "schema": {
              "type": "integer",
              "format": "int32"
            }
          }
        ],
        "responses": {
          "200": {
            "description": "Success"
          }
        }
      }
    },
    "/api/AvaliacaoTaking/produto": {
      "get": {
        "tags": [
          "Produto"
        ],
        "parameters": [
          {
            "name": "idcSituacao",
            "in": "query",
            "schema": {
              "type": "string"
            }
          }
        ],
        "responses": {
          "200": {
            "description": "Success"
          }
        }
      },
      "post": {
        "tags": [
          "Produto"
        ],
        "requestBody": {
          "content": {
            "application/json": {
              "schema": {
                "$ref": "#/components/schemas/ProdutoDominio"
              }
            },
            "text/json": {
              "schema": {
                "$ref": "#/components/schemas/ProdutoDominio"
              }
            },
            "application/*+json": {
              "schema": {
                "$ref": "#/components/schemas/ProdutoDominio"
              }
            }
          }
        },
        "responses": {
          "200": {
            "description": "Success"
          }
        }
      },
      "put": {
        "tags": [
          "Produto"
        ],
        "requestBody": {
          "content": {
            "application/json": {
              "schema": {
                "$ref": "#/components/schemas/ProdutoDominio"
              }
            },
            "text/json": {
              "schema": {
                "$ref": "#/components/schemas/ProdutoDominio"
              }
            },
            "application/*+json": {
              "schema": {
                "$ref": "#/components/schemas/ProdutoDominio"
              }
            }
          }
        },
        "responses": {
          "200": {
            "description": "Success"
          }
        }
      }
    },
    "/api/AvaliacaoTaking/produto/{Id}": {
      "get": {
        "tags": [
          "Produto"
        ],
        "parameters": [
          {
            "name": "Id",
            "in": "path",
            "required": true,
            "schema": {
              "type": "integer",
              "format": "int32"
            }
          }
        ],
        "responses": {
          "200": {
            "description": "Success"
          }
        }
      },
      "delete": {
        "tags": [
          "Produto"
        ],
        "parameters": [
          {
            "name": "Id",
            "in": "path",
            "required": true,
            "schema": {
              "type": "integer",
              "format": "int32"
            }
          }
        ],
        "responses": {
          "200": {
            "description": "Success"
          }
        }
      }
    },
    "/api/AvaliacaoTaking/produto/busca-pelo-codigo/{CodProduto}": {
      "get": {
        "tags": [
          "Produto"
        ],
        "parameters": [
          {
            "name": "CodProduto",
            "in": "path",
            "required": true,
            "schema": {
              "type": "string"
            }
          }
        ],
        "responses": {
          "200": {
            "description": "Success"
          }
        }
      }
    },
    "/api/AvaliacaoTaking/venda/busca-por-data": {
      "get": {
        "tags": [
          "Venda"
        ],
        "parameters": [
          {
            "name": "dataInicio",
            "in": "query",
            "schema": {
              "type": "string"
            }
          },
          {
            "name": "dataFim",
            "in": "query",
            "schema": {
              "type": "string"
            }
          }
        ],
        "responses": {
          "200": {
            "description": "Success"
          }
        }
      }
    },
    "/api/AvaliacaoTaking/venda/{CodVenda}": {
      "get": {
        "tags": [
          "Venda"
        ],
        "parameters": [
          {
            "name": "CodVenda",
            "in": "path",
            "required": true,
            "schema": {
              "type": "string"
            }
          }
        ],
        "responses": {
          "200": {
            "description": "Success"
          }
        }
      }
    },
    "/api/AvaliacaoTaking/venda": {
      "post": {
        "tags": [
          "Venda"
        ],
        "requestBody": {
          "content": {
            "application/json": {
              "schema": {
                "$ref": "#/components/schemas/VendaRequest"
              }
            },
            "text/json": {
              "schema": {
                "$ref": "#/components/schemas/VendaRequest"
              }
            },
            "application/*+json": {
              "schema": {
                "$ref": "#/components/schemas/VendaRequest"
              }
            }
          }
        },
        "responses": {
          "200": {
            "description": "Success"
          }
        }
      }
    }
  },
  "components": {
    "schemas": {
      "ClienteDominio": {
        "required": [
          "EndCliente",
          "NomCliente"
        ],
        "type": "object",
        "properties": {
          "Id": {
            "type": "integer",
            "format": "int32"
          },
          "IdcSituacao": {
            "type": "string",
            "nullable": true
          },
          "DescSituacao": {
            "type": "string",
            "nullable": true,
            "readOnly": true
          },
          "NomCliente": {
            "maxLength": 100,
            "minLength": 0,
            "type": "string"
          },
          "CodTelefone": {
            "type": "string",
            "nullable": true
          },
          "EndCliente": {
            "maxLength": 500,
            "minLength": 0,
            "type": "string"
          }
        },
        "additionalProperties": false
      },
      "FilialDominio": {
        "required": [
          "NomFilial"
        ],
        "type": "object",
        "properties": {
          "Id": {
            "type": "integer",
            "format": "int32"
          },
          "IdcSituacao": {
            "type": "string",
            "nullable": true
          },
          "DescSituacao": {
            "type": "string",
            "nullable": true,
            "readOnly": true
          },
          "NomFilial": {
            "maxLength": 100,
            "minLength": 0,
            "type": "string"
          }
        },
        "additionalProperties": false
      },
      "ProdutoDominio": {
        "required": [
          "CodProduto",
          "DescProduto",
          "NomProduto"
        ],
        "type": "object",
        "properties": {
          "Id": {
            "type": "integer",
            "format": "int32"
          },
          "IdcSituacao": {
            "type": "string",
            "nullable": true
          },
          "DescSituacao": {
            "type": "string",
            "nullable": true,
            "readOnly": true
          },
          "CodProduto": {
            "maxLength": 15,
            "minLength": 0,
            "type": "string"
          },
          "NomProduto": {
            "maxLength": 100,
            "minLength": 0,
            "type": "string"
          },
          "DescProduto": {
            "maxLength": 500,
            "minLength": 0,
            "type": "string"
          },
          "ValPrecoUnitario": {
            "maximum": 999999,
            "minimum": 0,01,
            "type": "number",
            "format": "double"
          }
        },
        "additionalProperties": false
      },
      "VendaRequest": {
        "type": "object",
        "properties": {
          "DthVenda": {
            "type": "string",
            "format": "date-time"
          },
          "NumCliente": {
            "maximum": 2147483647,
            "minimum": 1,
            "type": "integer",
            "format": "int32"
          },
          "NumFilial": {
            "maximum": 2147483647,
            "minimum": 1,
            "type": "integer",
            "format": "int32"
          }
        },
        "additionalProperties": false
      }
    },
    "securitySchemes": {
      "Bearer": {
        "type": "apiKey",
        "name": "token",
        "in": "header"
      }
    }
  },
  "security": [
    {
      "Bearer": [ ]
    }
  ]
}